hypershell/__init__.py
hypershell/client.py
hypershell/config.py
hypershell/server.py
hypershell/submit.py
hypershell/task.py
hypershell/cluster/__init__.py
hypershell/cluster/local.py
hypershell/cluster/remote.py
hypershell/cluster/ssh.py
hypershell/core/__init__.py
hypershell/core/config.py
hypershell/core/exceptions.py
hypershell/core/fsm.py
hypershell/core/heartbeat.py
hypershell/core/logging.py
hypershell/core/platform.py
hypershell/core/pretty_print.py
hypershell/core/queue.py
hypershell/core/remote.py
hypershell/core/signal.py
hypershell/core/sys.py
hypershell/core/tag.py
hypershell/core/template.py
hypershell/core/thread.py
hypershell/core/types.py
hypershell/core/uuid.py
hypershell/data/__init__.py
hypershell/data/core.py
hypershell/data/model.py
hypershell-2.7.2.dist-info/METADATA
hypershell-2.7.2.dist-info/WHEEL
hypershell-2.7.2.dist-info/entry_points.txt
hypershell-2.7.2.dist-info/licenses/LICENSE
hypershell-2.7.2.dist-info/RECORD
