Metadata-Version: 2.4
Name: hypershell
Version: 2.7.2
Summary: A cross-platform, high-throughput computing utility for processing shell commands over a distributed, asynchronous queue.
Author-email: Geoffrey Lentner <glentner@purdue.edu>
License-Expression: Apache-2.0
License-File: LICENSE
Keywords: command-line-tool,distributed-computing,high-performance-computing,high-throughput-computing,shell-scripting
Classifier: Development Status :: 5 - Production/Stable
Classifier: License :: OSI Approved :: Apache Software License
Classifier: Operating System :: MacOS
Classifier: Operating System :: Microsoft :: Windows
Classifier: Operating System :: POSIX :: Linux
Classifier: Programming Language :: Python :: 3.9
Classifier: Programming Language :: Python :: 3.10
Classifier: Programming Language :: Python :: 3.11
Classifier: Programming Language :: Python :: 3.12
Classifier: Programming Language :: Python :: 3.13
Classifier: Programming Language :: Python :: 3.14
Classifier: Topic :: Utilities
Requires-Python: >=3.9
Requires-Dist: cmdkit[toml]>=2.7.7
Requires-Dist: paramiko>=3.4.0
Requires-Dist: pyyaml>=6.0.1
Requires-Dist: rich>=13.7.1
Requires-Dist: sqlalchemy>=2.0.29
Requires-Dist: tomlkit>=0.13.2
Provides-Extra: postgres
Requires-Dist: psycopg2>=2.9.9; extra == 'postgres'
Provides-Extra: uuid7
Requires-Dist: uuid-utils>=0.10.0; extra == 'uuid7'
